{"consulate general of the united states, chennai": 1, "deputy high commission of sri lanka, chennai": 1, "victory war memorial": 1, "the grand marena": 1, "stella maris college, chennai": 1, "anna university school of architecture and planning": 1, "sikara service apartments": 1, "red sun hotel apartments": 1, "a. m. jain college": 1, "kollatti": 1, "perumbakkam": 2, "valasaravakkam": 2, "madras medical mission": 1, "grt temple bay beach resort": 1, "trident hilton chennai": 1, "thirumangalam, chennai": 1, "talabur": 1, "velachery aeri": 1, "ramakrishna mission vivekananda college": 1, "laurent & benon prm srv apt.-gst road": 1, "tirukkandalam": 1, "the forum vijaya": 1, "kammarpalaiyam": 1, "hotel pandian": 1, "victoria public hall": 1, "marina beach": 2, "hindu mission hospital, chennai": 1, "durga nagar": 1, "perungavur": 1, "ayyappa nagar": 1, "hotel manhattan": 1, "sikkarayapuram": 1, "anand institute of higher technology": 1, "pride": 1, "isha life": 1, "chennai": 2, "crowne plaza chennai adyar park": 1, "trident, chennai": 1, "mudichchur": 1, "valluvar kottam": 2, "mathuracheri": 1, "tamil nadu open university": 1, "olympia tech park": 1, "wadia nagar": 1, "vellanur": 2, "shastri nagar, goregaon": 1, "avadi": 2, "raheja towers, chennai": 1, "sipcot it park": 1, "the lotus service apartments": 1, "alinjivakkam": 1, "the checkers": 1, "e hotel": 1, "mayajaal": 1, "st. peter's college of engineering and technology": 1, "ymca college of physical education": 1, "mrf pace foundation": 1, "clarion hotel chennai": 1, "irulappattu": 1, "maduravoyal": 2, "royapuram": 2, "ayodhya mandapam": 1, "kalakshetra colony": 1, "mulacheri": 1, "egattur (kanchipuram district)": 1, "madras veterinary college": 1, "kosapet": 1, "general kumaramangalam colony": 1, "government general hospital, chennai": 1, "kandaiyur": 1, "ottiyanbakkam": 1, "vepery": 2, "ekkattuthangal metro station": 1, "sadayankuppam": 1, "st.thomas mount-cum-pallavaram": 1, "minjur": 2, "fishermans cove": 1, "queen mary's college, chennai": 1, "sree devi niwas": 1, "egmore": 2, "poonamalle": 1, "tambaram": 2, "star city hotel": 1, "athipattu pudunagar": 1, "my lady garden": 1, "kolathur, chennai": 1, "madavakam": 1, "palavakkam": 2, "regional railway museum, chennai": 1, "vadapalani": 2, "sheraton park hotel & tower": 1, "burma bazaar": 1, "dav school, adambakkam": 1, "kusapet": 1, "kumananchavadi": 1, "kuppam": 1, "shree motilal kanhaiyalal fomra institute of technology": 1, "quality inn sabri": 1, "chellammal women's college": 1, "spencer plaza": 1, "palavantangai": 1, "vandalur reserve forest": 1, "m. a. chidambaram stadium": 1, "lily pond": 1, "taz kamar inn": 1, "perunkalattu": 1, "courtyard by marriott chennai": 1, "selaiyur": 1, "somerset greenways": 1, "gopalapuram": 1, "kumaran nagar": 1, "chinnasekkadu": 2, "tambaram sanatorium": 1, "seven wells north": 1, "nellikkuppam": 1, "anna university, chennai": 1, "pondy bazaar": 1, "kotturpuram railway station": 1, "presidency college, chennai": 1, "lakshmipuram": 1, "moore market complex railway station": 1, "don bosco matriculation higher secondary school, chennai": 1, "thirumullaivoyal": 2, "eranavakkam": 1, "southern crest": 1, "thiruvallikeni railway station": 1, "chennai port": 1, "wesley higher secondary school": 1, "puliantope": 1, "ekkattuthangal": 1, "my fortune, chennai": 1, "ibis chennai sipcot": 1, "arr chennai gateway": 1, "otteri": 2, "puzhal aeri": 1, "teynampet": 2, "the island, chennai": 1, "manappakkam": 1, "siruseri": 2, "hotel dee cee manor": 1, "vestin park": 1, "ambattur station": 1, "taramani railway station": 1, "fort saint george": 1, "thousand lights mosque": 1, "pudupet": 1, "madhavaram junction": 1, "anna centenary library": 1, "chennai mathematical institute": 1, "rajakilpakkam": 2, "kilpauk garden": 1, "covelong": 2, "chromepet railway station": 1, "government dental hospital and college, chennai": 1, "jawaharnagar": 1, "stella matutina college of education": 1, "dr. mgr-janaki college of arts and science for women": 1, "nehru nagar": 2, "skywalk hotel": 1, "southern railway zone": 1, "le waterina resort": 1, "exnora international": 1, "assisi nagar": 1, "sottuperumbedu": 1, "nikhil palace": 1, "cholavaram tank": 1, "aruna": 1, "jw marriott chennai": 1, "taj club house": 1, "britto school": 1, "tamil nadu legislative assembly": 1, "kovilambakkam": 1, "periyar nagar": 1, "pulli lyon": 1, "royal star": 1, "sdat tennis stadium": 1, "padmanabha nagar": 1, "park sheraton": 1, "kathipara junction": 1, "attupakkam": 1, "thirumayilai railway station": 1, "the gateway hotel itexpressway": 1, "mgm dizzee world": 1, "peravallur": 2, "kannianpalaiyam": 1, "gemini inn": 1, "ammapettai": 1, "birla planetarium, chennai": 1, "puzhuthivakkam": 1, "madras boat club": 1, "residency towers chennai": 1, "villivakkam": 2, "erukkancheri": 1, "apparswami temple": 1, "sboa school & junior college": 1, "chitlapakkam aeri": 1, "panagal park": 1, "madras observatory": 1, "santhi nagar": 1, "vaduvapalaiyam": 1, "radisson blu hotel chennai city centre": 1, "the vijay park": 1, "george town, chennai": 1, "semmencherry": 2, "laws bridge": 1, "ullagaram": 1, "sanjivarayanpet": 1, "ayanavaram": 2, "largest human flag of india": 1, "hotel maurya international": 1, "attippedu": 1, "madras export processing zone": 1, "lemon tree": 1, "new erumai vetti palayam": 1, "puripakkam": 1, "kundrathur": 1, "quality hotel sabari classic": 1, "sri sankara senior secondary school": 1, "arumbakkam": 2, "jawahar nagar, chennai": 1, "naravarikuppam": 2, "central institute of plastics engineering and technology (india)": 1, "the park, chennai": 1, "chinnakudal": 2, "kottakuppam": 1, "st. thomas mount": 1, "oragadam, ambattur": 1, "seven wells south": 1, "injambakkam": 2, "savera": 1, "puduvayal": 1, "royapuram fishing harbour": 1, "ayalcheri": 1, "budur": 1, "meenakshi sundararajan engineering college": 1, "elephinstone bridge": 1, "savera hotel": 1, "prathyangira devi temple, shollinganallur": 1, "raj palace": 1, "spi cinemas": 1, "rain tree mount road": 1, "nungambakkam high road": 1, "mannady": 1, "the leela palace chennai": 1, "greenways road railway station": 1, "green meadows resort": 1, "raintree hotel, anna salai": 1, "radha park inn chennai": 1, "chinmaya nagar": 1, "anicut": 1, "velammal engineering college": 1, "hotel le repose": 1, "kothawal chavadi": 2, "central polytechnic chennai": 1, "the iris hotel chennai": 1, "nazarathpuram": 1, "ria s guest house": 1, "singara garden": 1, "chennai beach": 1, "puzhal central prison": 1, "ambica empire patrimonio": 1, "hotel kensington": 1, "george town": 1, "novotel chennai sipcot": 1, "triumph of labour": 1, "hablis hotel chennai": 1, "st. thomas garrison church": 1, "radisson resort temple bay": 1, "mattews railway colony": 1, "st andrew's church, chennai": 1, "tirumailai": 1, "varadancheri": 1, "royal regency": 1, "asiana place": 1, "arumbakkam metro station": 1, "phoenix market city (chennai)": 1, "mangal aeri, chennai": 1, "ennore": 1, "tirusulam railway station": 1, "smart haven corporate rooms and residences": 1, "radha regent hotel, chennai": 1, "surappattu": 1, "radisson blu hotel chennai": 2, "kambar nagar": 1, "bharat insurance building": 1, "ashok nagar, chennai": 1, "chettinad health city": 1, "mambalam railway station": 1, "olcott memorial high school": 1, "grant lyon": 1, "puzhal": 1, "pudupedu": 1, "st. joseph's college of engineering": 1, "mandavelli": 1, "minakshi ammanpet": 1, "new woodlands hotel": 1, "mettuppalaiyam": 1, "hutton bridge": 1, "perungalathur": 1, "chromepet": 2, "taj coromandel": 2, "indira nagar railway station": 1, "madhya kailash junction": 1, "thattankulam": 1, "chepauk palace": 1, "kollacheri": 1, "m a chidambaram cricket stadium": 1, "st. george's cathedral, chennai": 1, "padianallur": 1, "tondiarpet": 2, "mandaveli railway station": 1, "central institute of brackish water aquaculture": 1, "chemman cherry": 1, "adambakkam": 2, "sithalapakkam": 1, "marmalang bridge": 1, "the retreat hotel": 1, "madambakkam": 1, "urapakkam railway station": 1, "alpha college of engineering": 1, "adyar river": 2, "gokhale hall": 1, "minjur railway station": 1, "elliots beach": 1, "padi, chennai": 1, "walajah bridge": 1, "m. c. c. higher secondary school": 1, "skr engineering college": 1, "sembium": 1, "st. peter's engineering college, avadi": 1, "v. o. c. nagar railway station": 1, "church of our lady of light, chennai": 1, "emerald": 1, "quality inn sabari": 1, "vaishnavi nagar": 1, "executive comfort": 1, "karapakkam": 1, "kosisttalaiyar river": 1, "marsan lodge": 1, "kalavakkam": 1, "vasanth tv": 1, "sangeetha residency": 1, "chennai airport flyover": 1, "avnb towers": 1, "dakshinachitra": 1, "agaram": 1, "chromepet flyover": 1, "puliyur, nagapattinam": 1, "adyar library": 1, "tolgate": 1, "indira nagar": 1, "mars.": 1, "national institute of siddha": 1, "alwarpet": 2, "adyar, chennai": 1, "mgm eastwoods": 1, "sathyabama university": 1, "thandrayankuppam": 1, "kelambakkam": 2, "asian college of journalism, chennai": 1, "jeppiaar engineering college": 1, "athipattu pudhunagar railway station": 1, "edward elliot's beach": 1, "virapuram": 1, "tambaram air force station": 1, "kannammapet": 1, "grt grand, chennai": 1, "seemapuram": 1, "padi railway station": 1, "bollineni hillside": 1, "neyveli": 1, "chepauk railway station": 1, "koyambedu junction": 1, "pallavaram railway station": 1, "crescent park": 1, "athipattu railway station": 1, "kantmavarinattam": 1, "adyar ananda bhavan": 1, "kumaran nagar, chennai": 1, "uno the business hotel": 1, "tirumudipakkam": 1, "sholavaram aeri": 1, "dr. ambedkar government law college, chennai": 1, "panimalar engineering college": 1, "selaivayal": 1, "tambaram sanatorium railway station": 1, "naduvankarai": 1, "lemon tree hotel shimona chennai": 1, "abu palace": 1, "radisson blu city centre": 1, "radisson grt hotel": 1, "napiers bridge": 1, "chennai fort railway station": 1, "manthaiveli": 1, "pudupalaiyam": 1, "anna memorial": 1, "alpha arts & science college": 1, "karl schmidt memorial": 1, "kumarasamy nagar north": 1, "mugalivakkam": 2, "d.a.v. boys senior secondary school": 1, "elandacheri": 1, "kudiraipallam": 1, "k. k. nagar, chennai": 1, "sengadu": 1, "vadaperumbakkam": 1, "nandiyambakkam": 1, "mettukuppam": 1, "chennai park railway station": 1, "ginger chennai - vadapalani": 1, "jawaharlal nehru stadium (chennai)": 1, "broadway bus terminus": 1, "korattur": 2, "abhirami mega mall": 1, "blossoms serviced apartments": 1, "chennai trade centre": 1, "chemplast cricket ground": 1, "sridevi nrithyalaya": 1, "nayagara hotel": 1, "hotel pearl international": 1, "itc grand chola": 1, "commander-in-chief bridge": 1, "kohinoor asiana hotel": 1, "kallikuppam, ambattur": 1, "saidapet": 2, "perfect haven egmore serviced apartments": 1, "kotivakkam": 1, "vallur": 1, "athipattu": 1, "velachcheri": 1, "ayappakkam": 1, "basin bridge railway station": 1, "hyatt regency chennai": 2, "chennai beach railway station": 1, "san thome": 1, "iit madras": 1, "kerala vidhyalayam higher secondary school": 1, "guindy railway station": 1, "ariyappancheri": 1, "reddipalaiyam": 1, "attippattu": 1, "railway car shed": 1, "ko-su-mani nagar": 1, "periyar nagar, chennai": 1, "krishnampet": 1, "all india radio transmitting station": 1, "perfect haven omr": 1, "roja muthiah research library": 1, "police headquarters building, chennai": 1, "higginbotham's": 1, "kuruvimedu": 1, "perambur": 2, "west mambalam": 1, "poompuhar": 1, "mint street, chennai": 1, "hotel holy night": 1, "ascendas it park": 1, "akshar \u00e1rbol international school": 1, "hotel shelter": 1, "thirumangalam, tiruchi": 1, "greenways road": 1, "mctm chidambaram chettyar international ib school": 1, "pangambedu": 1, "gojan school of business and technology": 1, "vengavasal": 1, "periamet": 2, "thiruvanmiyur": 1, "cowl bazaar": 1, "north chennai thermal power station": 1, "korukkupet": 2, "chetput": 1, "park": 1, "ambica empire (heritage)": 1, "hotel lake view park": 1, "peace park inn chennai": 1, "perungalathur railway station": 1, "kovur, kanchipuram": 1, "thalambur": 1, "national public school, chennai": 1, "loyola institute of business administration": 1, "breeze hotel": 1, "maduraivayal": 1, "bangarampettaichori": 1, "padiyanallur": 1, "institute of mathematical sciences, chennai": 1, "uttandi": 1, "the park chennai": 1, "theeyampakkam": 1, "thiruvanmiyur railway station": 1, "kattupakkam": 1, "manjambakkam": 2, "pannivakkam": 1, "periyasekkadu": 1, "polichalur": 1, "periyakudal": 2, "chitlapakkam": 1, "moulivakkam": 1, "sowcarpet": 2, "azhagiri nagar": 1, "kathivakkam": 2, "moolakadai": 2, "glm meridian": 1, "hotel chinnass": 1, "wyand & company": 1, "nesapakkam": 2, "government hospital of thoracic medicine, chennai": 1, "maruderi": 1, "hotel queensway park": 1, "saint thomas mount": 1, "tidel park": 1, "meenakshi academy of higher education and research": 1, "vadanemali": 1, "perambur carriage works": 1, "shan royal": 1, "jp chennai": 1, "vichchur": 1, "selaiyu": 1, "tri sea residency": 1, "hotel emerald park": 1, "hotel nandini palace": 1, "royal paris": 1, "theosophical society adyar": 1, "annanur": 2, "shasthri nagar": 1, "mgr memorial": 1, "guindy national park": 2, "pachaiyappa's college": 1, "spic building, chennai": 1, "saint theresa church, perambur": 1, "virugambakkam": 2, "erumaivettippalaiyam": 1, "puthagaram, chennai": 1, "abhiramapuram": 1, "the pride hotel chennai": 1, "konnur tank": 1, "tirurageswaram": 1, "madhavamani avenue": 1, "ragas dental college & hospital": 1, "kodungaiyur": 2, "kumaraswamy nagar": 1, "sri sivasubramaniya nadar college of engineering": 1, "coromandel plaza": 1, "regional meteorological centre, chennai": 1, "madras high court": 1, "chettinad vidyashram": 1, "kalikambal temple": 1, "jawaharlal nehru stadium": 1, "radisson blu hotel grt": 1, "tharamani": 2, "vgp universal kingdom": 1, "st. peter's church, royapuram": 1, "kottivakkam": 1, "choolai": 2, "benzz park tulip": 1, "mullam": 1, "government college of fine arts, chennai": 1, "eranavur": 1, "sepakkam": 1, "chennai citi centre": 1, "mkb nagar": 1, "gandhi nagar, chennai": 1, "jaffarkhanpet": 1, "manali new town": 1, "periya aeri": 1, "chetput railway station": 1, "shiva temple": 1, "konnur": 1, "2005 november chennai stampede": 1, "m.o.p. vaishnav college for women": 1, "priyadarshini park": 1, "vgp golden beach resort": 1, "kek accommodation & annex": 1, "shri devi park": 1, "residency towers": 1, "ennore creek": 1, "san thome basilica": 1, "vyasarpadi jeeva railway station": 1, "s.a. engineering college": 1, "agraharam": 1, "kasturba nagar railway station": 1, "puludivakkam": 1, "quaid-e-millath government college for women": 1, "kathivakkam railway station": 1, "good shepherd convent, chennai": 1, "taramani": 1, "karambakkam": 1, "holy angels anglo indian higher secondary school": 1, "alapakam": 1, "hospital bridge": 1, "shenoy nagar": 2, "thirumangalam": 1, "covelong point": 1, "tvk nagar, chennai": 1, "manali, chennai": 1, "anakaputtur": 1, "arihant majestic towers": 1, "kosappur": 2, "kattivakkam": 1, "trustpuram": 2, "madras medical college": 1, "ambattur taluk": 1, "hotel esthell": 1, "saint patrick's cathedral, chennai": 1, "guindy thiru vi ka estate": 1, "p. s. senior secondary school": 1, "lakshmipuram, chennai": 1, "hotel abu palace": 1, "st. lazarus' church, chennai": 1, "madras school of economics": 1, "chennai open": 1, "tiruvottiyur railway station": 1, "rajaji hall": 1, "kurambakkam": 1, "butterfly group of houseboat": 1, "karanodai": 1, "national institute of ocean technology": 1, "otteri nullah": 2, "grt temple bay": 1, "keranaipudchcheri": 1, "thirumalai nagar": 1, "oriental inn": 1, "american international school\u2013chennai": 1, "asiana": 1, "karunanidhi nagar": 1, "geography of chennai": 1, "jambuli": 1, "napier bridge": 1, "perungudi": 2, "perambur locoworks": 1, "ekkaduthangal": 1, "fisherman's cove": 1, "st. bede's anglo indian higher secondary school": 1, "fortis malar hospital": 1, "nayar": 1, "sri balaji temple, t. nagar": 1, "park town": 1, "hindu college railway station": 1, "shylee niwas service apartment": 1, "tiruvanmiyur": 1, "ramada chennai egmore": 1, "balaji dental and craniofacial hospital": 1, "sembiyam": 1, "kilpauk": 2, "vichoor": 1, "nekkunram": 1, "vembedu": 1, "ambedkar manimandapam, chennai": 1, "unamaucheri": 1, "thiru-vi-ka nagar": 1, "saint andrews bridge": 1, "spectrum mall (chennai)": 1, "adyar": 1, "kishkinta": 1, "raj residency": 1, "dharmamurthi rao bhahadur calavala cunnan chetty's hindu college": 1, "appavoo nagar": 1, "grace garden": 1, "taj club house chennai": 1, "royal plaza chennai": 1, "loyola college, chennai": 1, "sholavaram": 1, "srimathi sundravalli memorial school": 1, "bell hotel chennai": 1, "southern railway headquarters, chennai": 1, "tamil nadu dr. m.g.r. medical university": 1, "thirumullaivoyal railway station": 1, "hotel victoria": 1, "sokkanallur": 1, "pallipattu": 1, "rajiv gandhi salai": 1, "mehtanagar": 1, "tirusulam": 1, "gkm college of engineering and technology": 1, "manjankaranai": 1, "ramireddipalaiyam": 1, "mylapore": 2, "greenpark hotel": 1, "raja annamalaipuram": 2, "anakaputhur": 2, "gandhi mandapam (chennai)": 1, "satyamurti nagar": 1, "cherian nagar north": 1, "chennai mofussil bus terminus": 1, "doctor radhakrishna nagar": 1, "le royal meridien, chennai": 1, "poonamallee": 1, "ezhilagam": 1, "vyasarpadi jeeva": 1, "jaigopal garodia vivekananda vidyalaya": 1, "kutti paracheri": 1, "vallur thermal power project": 1, "sathiya moorthy nagar": 2, "anderson church, chennai": 1, "kkd nagar": 1, "kondangi": 1, "sadaiyankuppam": 1, "connemara public library": 1, "radha regent": 1, "nanmangalam": 1, "hotel chariot": 1, "king s hotel": 1, "siege of madras": 1, "british deputy high commission, chennai": 1, "vyasarpadi": 2, "madras music academy": 1, "peddanaikenpet": 1, "loyola-icam college of engineering and technology": 1, "aminjikarai": 2, "mathur, chennai": 1, "korukkupet railway station": 1, "doveton": 1, "mambalam": 2, "buckingham canal": 1, "velachery railway station": 1, "ennore thermal power station": 1, "avadi railway station": 1, "annai violet arts and science college": 1, "royal southern": 1, "jutkapuram metro station": 1, "wesley church, egmore": 1, "kattrivedu": 1, "mgr nagar": 1, "the national art gallery (chennai)": 1, "2012 indian premier league opening ceremony": 1, "edmpalaiyam": 1, "hindu senior secondary school, indira nagar": 1, "aloft chennai omr it expressway": 1, "ramada rajpark": 1, "choolaimedu": 1, "pattaravakkam railway station": 1, "perungudi railway station": 1, "sanarpalaiyam": 1, "madras christian college": 1, "tamil nadu": 1, "amet university": 1, "madhavaram": 2, "st. mary's church, chennai": 1, "valudalambedu": 1, "anna university": 1, "andarkuppam": 1, "pon vidyashram": 1, "kcg college of technology": 1, "anna nagar tower park": 1, "the new college, chennai": 1, "mayor radhakrishnan stadium": 1, "asan memorial senior secondary school": 1, "sea shell residency": 1, "doctor vijayaraghavulu nagar": 1, "palavedu": 1, "barathidasan nagar": 1, "crescent inn": 1, "madras presidency": 1, "laurent & benon premium service apt gst road": 1, "vanavani matriculation higher secondary school": 1, "doveton corrie protestant schools association": 1, "navalar nedunchezian nagar": 1, "hindu senior secondary school, triplicane": 1, "b. s. abdur rahman university": 1, "chemplast sanmar": 1, "nagappa nagar": 1, "perambur flyover park": 1, "ambattur aeri": 1, "jalladiampet": 1, "puliyur": 1, "st. kevin's anglo indian high school": 1, "chattram": 1, "pallipatu": 1, "jeeva nagar north": 1, "shastri nagar": 1, "kulattur": 1, "the lotus service apartments venkatraman street": 1, "itc park sheraton and towers": 1, "cooum river": 2, "taiyur": 1, "sboa matriculation and higher secondary school, chennai": 1, "konnur (rural)": 1, "blue cross of india": 1, "benz park tulip": 1, "vels university": 1, "accord metropolitan": 1, "subramania nagar": 1, "vivanta by taj - fishermans cove": 1, "peddanaickenpettah": 1, "vellala street": 1, "reserve bank of india, south zonal office": 1, "senate house (university of madras)": 1, "sir theagaraya college": 1, "fortel": 1, "palavanthangal": 1, "kaikalapettai": 1, "perambur loco works railway station": 1, "alwarthirunagar": 1, "velachery": 1, "chintadripet": 2, "mannivakkam": 1, "sembakkam": 1, "jagannadapuram": 1, "deccan plaza": 1, "kohinoor asiana chennai": 1, "gopalapuram, chennai": 1, "chennai egmore railway station": 2, "mahalaya residency": 1, "vaishnavi temple": 1, "kasturiba nagar": 1, "banavedutottam": 1, "the park pod": 1, "general post office, chennai": 1, "radisson blu resort": 1, "somasundirapedu": 1, "purasawalkam": 2, "women's christian college, chennai": 1, "ramee mall": 1, "harrisons": 1, "ennore railway station": 1, "kasigobind temple": 1, "pattabiram station": 1, "mel pakkam": 1, "taj mount road": 1, "indian institute of technology madras": 1, "adambakkam railway station": 1, "kadapakkam, chennai": 1, "vanagaram": 1, "safire theatre complex": 1, "muttukadu boat house": 1, "st. thomas mount railway station": 1, "gmr vasavi diesel power plant": 1, "vallurnattam": 1, "samudra inn": 1, "sona s inn chennai": 1, "wimco nagar railway station": 1, "chintadripet railway station": 1, "dr. gurusamy bridge": 1, "venkatapuram": 1, "keys": 1, "gandhi nagar": 1, "mambakkam": 1, "madras war cemetery": 1, "pattaravakkam": 1, "chennai metropolitan development authority": 1, "medavakkam": 1, "consulate general of the russian federation in chennai": 1, "mangadu": 1, "pattalam, chennai": 1, "srinagar": 1, "quality inn sabri classic": 1, "ganesapuram": 1, "madiyur": 1, "entre": 1, "arignar anna zoological park": 1, "sembium-ayanavaram municipality": 1, "park town, chennai": 1, "prince matriculation higher secondary school": 1, "citrus hotel east coast road chennai": 1, "nanmangalam reserve forest": 1, "breeze": 1, "perambur carriage works railway station": 1, "salt cotaurs": 2, "hotel park view": 1, "pallikaranai": 2, "chandra mall": 1, "kilpauk medical college": 1, "zen garden": 1, "parry's corner": 1, "vilangadupakkam": 1, "gymkhana club, chennai": 1, "adarsh vidyalaya higher secondary school": 1, "hotel mars deluxe": 1, "thyagaraya nagar": 1, "royapettah": 2, "madha engineering college": 1, "amir mahal": 2, "chennai contract carriage bus terminus": 1, "chetput (chennai)": 1, "thulashi park": 1, "perambur railway station": 1, "peerkankaranai": 1, "foreshore estate": 1, "manapakkam": 1, "westin chennai velachery": 1, "kodambakkam bridge": 1, "nalambur": 1, "surutapalli": 1, "tondiarpet railway station": 1, "basavanpalaiyam": 1, "anna flyover": 1, "nerkunram": 2, "rajarathinam stadium": 1, "basin bridge": 1, "chennai central railway station": 1, "lic building": 1, "t. nagar": 1, "hotel chennai deluxe": 1, "simapuram": 1, "kalakshetra": 1, "yedapalaiyam": 1, "hotel manickam grand": 1, "bkr grand": 1, "raja annamalai chettiar hall": 1, "anna nagar west": 2, "hotel kingss park": 1, "komaleeswaranpet": 1, "kovilancheri": 1, "charnockite, st. thomas mount": 1, "jerusalem college of engineering, chennai": 1, "citrus ecr chennai": 1, "hilton chennai": 1, "kathirvedu": 1, "armenian church, chennai": 1, "tamil nadu physical education and sports university": 1, "eagangipuram": 1, "united india colony": 1, "willingdon bridge": 1, "bentinck school, vepery": 1, "t s narayanaswami college of arts and science": 1, "fortune select palms": 1, "chennai park town railway station": 1, "atturkandigai": 1, "pulal tank": 1, "maduravoyal junction": 1, "the rain tree": 1, "dept of cse": 1, "vivanta taj- fisherman's cove": 1, "guindy race course": 1, "kondakarainattam": 1, "manali": 1, "thenral": 1, "beverly": 1, "porur": 2, "sivaram": 1, "thangamani matriculation higher secondary school": 1, "kavanur": 1, "leela palace chennai": 1, "the gateway hotel it expressway chennai": 1, "quibble island": 1, "spring": 1, "sir ivan stedeford hospital": 2, "light house": 1, "government museum, chennai": 1, "subbareddipalaiyam": 1, "alagappa college of technology": 1, "surapet": 1, "irumbuliyur junction": 1, "movuthambedu": 1, "ramanujan it city": 1, "kosasthalaiyar river": 1, "chengalvaraya naicker polytechnic college": 1, "alandur": 2, "amman temple": 1, "anna salai": 1, "park hyatt chennai": 1, "days inn deccan plaza": 1, "raj bhavan (chennai)": 1, "chennai snake park trust": 1, "chola sheraton": 1, "nungambakkam": 2, "madras institute of technology": 1, "radha regent - a sarovar hotel chennai": 1, "guruvayal": 1, "ambattur railway station": 1, "koyambedu": 2, "shylee niwas service apartment anna nagar": 1, "tamil nadu government multi super speciality hospital": 1, "kences inn hotel": 1, "mgm beach resorts": 1, "ashtalakshmi temple, chennai": 1, "senthil nagar": 1, "kodambakkam": 2, "statue of thomas munro": 1, "ambica empire": 1, "puzhuthivakkam railway station": 1, "sri muthukumaran institute of technology": 1, "annanur railway station": 1, "international tech park, chennai": 1, "tirusulam station": 1, "ambattur": 2, "choolai medu": 1, "thodhunter nagar": 1, "keys katti-ma": 1, "washermanpet": 2, "ranganathan street": 1, "villivakkam railway station": 1, "ariyanvayal": 1, "triplicane big mosque": 1, "doctor radhakrishna nagar south": 1, "pakkipuram": 1, "narayanas arihant ocean tower": 1, "taj connemara": 2, "viraraghavapuram": 1, "central": 1, "ampa skywalk": 1, "urapakkam,kanchipuram": 1, "hotel mount heera": 1, "integral coach factory": 1, "kalaimagal nagar": 1, "udayam theatre": 1, "oggiyamduraipakkam": 1, "raintree st marys": 1, "mudichur": 1, "pattamandaloheri": 1, "mallika residency": 1, "college bridge": 1, "balaji nagar": 1, "kodangiyur": 1, "muthialpet": 1, "ashok nagar": 1, "cherian nagar south": 1, "iyyapanthangal": 1, "siruvallur": 1, "the accord metropolitan": 1, "pammal": 2, "korattur railway station": 1, "radisson blu resort temple bay": 1, "kings matriculation higher secondary school": 1, "nodlur": 1, "edayanchavadi": 1, "korttalaiyar river": 1, "tiruvottiyur": 2, "pallavaram": 2, "thenpudupattu": 1, "light house railway station": 1, "wimco nagar": 1, "suvi transit accommodation chrompet": 1, "meenambakkam": 2, "ambattur tank": 1, "the chamiers park": 1, "thaiyur": 1, "st. john's matriculation higher secondary school alwarthirunagar": 1, "rangarajapuram": 1, "angadu": 1, "vellivayal": 2, "tamil nadu dr. ambedkar law university": 1, "murugappa polytechnic college": 1, "alsa mall": 1, "emarald chennai": 1, "mettupalaiyam": 1, "pattamandiri": 1, "green park hotel": 1, "st. marys school of management": 1, "madipakkam": 2, "thousand lights": 1, "anna nagar": 2, "comfort inn marina towers": 1, "uembilivaram": 1, "kolapakkam": 1, "world bank office, chennai": 1, "jaya suriya engineering college": 1, "ernavoor": 1, "nanganallur": 1, "golden beach, chennai": 1, "vallalar nagar": 1, "triplicane": 2, "ramada raj park inn": 1, "arunachaleswaranpet": 1, "jeeva nagar south": 1, "tiruverkadu": 1, "mar gregorios college of arts and science, chennai": 1, "dr. m.g.r. educational and research institute": 1, "hotel mars classic": 1, "ramapuram, chennai": 1, "sholinganallur": 2, "washermanpet railway station": 1, "ripon building": 1, "itc grand chola hotel": 1, "fort": 1, "ennur": 1, "grt grand chennai": 1, "ekambareswarar temple, chennai": 1, "kullattur": 1, "meddappakkam": 1, "pattabiram east depot railway station": 1, "anna nagar railway station": 1, "ambassador pallava": 1, "sekkanjeri": 1, "guindy": 2, "king institute of preventive medicine and research": 1, "alamadi": 1, "madras institute of orthopaedics and traumatology": 1, "east tambaram": 1, "indira nagar, chennai": 1, "lighthouse, chennai": 1, "college of engineering, guindy": 1, "basin bridge gas turbine power station": 1, "mathur mmda park": 1, "kannigaipper": 1, "vadapurambakkam": 1, "chinnamalai": 1, "vandalur": 2, "vivanta by taj-connemara": 1, "regional institute of ophthalmology and government ophthalmic hospital, chennai": 1, "gold souk grande mall chennai": 1, "arasankalani": 1, "kallamchavadi": 1, "meenakshi college for women": 1, "nandiambakkam railway station": 1, "express avenue": 1, "raja nagar": 1, "vadakandigai": 1, "selavayal": 1, "vivekanandar illam": 1, "pallijkarani": 1, "kilkattalai": 1, "vadapalani andavar temple": 1, "thathankuppam": 1, "pudu vannarpet": 1, "tamil nadu thowheed jamath": 1, "raintree annasalai": 1, "cholavaram": 1, "nandambakkam": 2, "moovarasampettai": 1, "hyatt chennai": 1, "bandikavanur": 1, "anna university k b chandrashekar research centre": 1, "madras crocodile bank trust": 1, "ennore port": 1, "porur aeri": 1, "santhome": 1, "ainsley canal": 1, "navalur": 1, "vijayanagar bus terminus": 1, "hindu higher secondary school": 1, "kotturpuram": 2, "bharath university": 1, "jaya pushpam": 1, "neelankarai": 2, "annadanakakavakkam": 1, "varasiddhi vinayaka temple": 1, "mogappair": 1, "tamil nadu public service commission": 1, "pazhavanthangal railway station": 1, "old erumai vetti palayam": 1, "kamaraja nagar": 1, "chennai port trust centenary building": 1, "stanley medical college": 1, "besant nagar": 2, "j.n.n institute of engineering": 1, "nandanam": 2, "ponniammanmedu": 2, "le royal meridien chennai": 1, "madras central prison": 1, "chennai suburban railway": 1, "chepauk": 2, "cosmopolitan club (chennai)": 1, "km music conservatory": 1, "chennai international airport": 2, "qi sabri": 1, "basilica of the national shrine of st.thomas": 1, "saligramam": 2, "old jail road, chennai": 1, "abu sarovar portico": 1, "mukhdwaram": 1}